{
  "site_name": "nextdoor.com",
  "source_path": "site_sources/nextdoor.com/source.html",
  "injected_source_path": "injected_sites/nextdoor.com/aria-meter-name/source.html",
  "rule_md_path": "deque_md/aria-meter-name.md",
  "rule": "aria-meter-name",
  "a11y_error": "aria-meter-name",
  "expected_rule_id": "aria-meter-name",
  "injection_script_path": "injected_sites/nextdoor.com/aria-meter-name/injection_script.js",
  "rationale": "Adds a role=\"meter\" element with required value attributes but no accessible name (no aria-label, aria-labelledby, or title), which triggers the aria-meter-name rule."
}