{
  "site_name": "nextdoor.com",
  "source_path": "site_sources/nextdoor.com/source.html",
  "injected_source_path": "injected_sites/nextdoor.com/aria-toggle-field-name/source.html",
  "rule_md_path": "deque_md/aria-toggle-field-name.md",
  "rule": "aria-toggle-field-name",
  "a11y_error": "aria-toggle-field-name",
  "expected_rule_id": "aria-toggle-field-name",
  "injection_script_path": "injected_sites/nextdoor.com/aria-toggle-field-name/injection_script.js",
  "rationale": "Adds a custom element with role=\"switch\" and aria-checked but without any accessible name, triggering the aria-toggle-field-name rule."
}